equator_qa/__init__.py
equator_qa/charting.py
equator_qa/llmscalls.py
equator_qa/prompts.py
equator_qa/stats.py
equator_qa/utils.py
equator_qa/vectordb.py
equator_qa/assets/EQUATOR-Framework.png
equator_qa/data/linguistic_benchmark.json
equator_qa-1.0.3.dist-info/LICENSE
equator_qa-1.0.3.dist-info/METADATA
equator_qa-1.0.3.dist-info/WHEEL
equator_qa-1.0.3.dist-info/entry_points.txt
equator_qa-1.0.3.dist-info/top_level.txt
equator_qa-1.0.3.dist-info/RECORD
