Metadata-Version: 2.2
Name: equator_qa
Version: 1.0.3
Summary: Equator: A Deterministic Framework for Evaluating LLM Reasoning with Open-Ended Questions.
Author-email: Ray Bernard <ray.bernard@outlook.com>
License: MIT
Keywords: LLM evaluation,open-ended questions,reasoning framework
Classifier: Development Status :: 4 - Beta
Classifier: Intended Audience :: Developers
Classifier: Programming Language :: Python :: 3
Classifier: Programming Language :: Python :: 3.6
Classifier: Programming Language :: Python :: 3.7
Classifier: Programming Language :: Python :: 3.8
Classifier: Programming Language :: Python :: 3.9
Classifier: License :: OSI Approved :: MIT License
Requires-Python: >=3.6
License-File: LICENSE
Requires-Dist: numpy>=1.18.0
Requires-Dist: requests>=2.25.0
Requires-Dist: jupyter
Provides-Extra: dev
Requires-Dist: pytest; extra == "dev"
Requires-Dist: flake8; extra == "dev"
